native_extensions.cpython-36m-x86_64-linux-gnu.so
rook/__init__.py
rook/__main__.py
rook/atfork.py
rook/auto_start.py
rook/config.py
rook/factory.py
rook/file_utils.py
rook/fork_utils.py
rook/git.py
rook/interface.py
rook/machine.py
rook/pyspark_daemon.py
rook/rookout-config.json
rook/rookout_json.py
rook/serverless.py
rook/singleton.py
rook/trigger_services.py
rook/user_warnings.py
rook/utils.py
rook/version.py
rook/augs/__init__.py
rook/augs/aug.py
rook/augs/aug_factory.py
rook/augs/aug_rate_limiter.py
rook/augs/augs_manager.py
rook/augs/limit_manager.py
rook/augs/actions/__init__.py
rook/augs/actions/action_run_processor.py
rook/augs/conditions/__init__.py
rook/augs/conditions/if_condition.py
rook/augs/locations/__init__.py
rook/augs/locations/http_server_handler.py
rook/augs/locations/location.py
rook/augs/locations/location_exception_handler.py
rook/augs/locations/location_file_line.py
rook/augs/locations/location_log_handler.py
rook/augs/processor_extensions/__init__.py
rook/augs/processor_extensions/namespaces/__init__.py
rook/augs/processor_extensions/namespaces/log_record_namespace.py
rook/collect/__init__.py
rook/collect/exception_collector.py
rook/com_ws/__init__.py
rook/com_ws/agent_com_ws.py
rook/com_ws/command_handler.py
rook/com_ws/information.py
rook/com_ws/linux_distribution.py
rook/com_ws/output_ws.py
rook/com_ws/poll_select.py
rook/com_ws/selectable_event.py
rook/com_ws/selectable_queue.py
rook/com_ws/socketpair_compat.py
rook/com_ws/token_bucket.py
rook/com_ws/agent_com_impel/__init__.py
rook/com_ws/agent_com_impel/agent_com_base.py
rook/com_ws/agent_com_impel/multithread_agent_com.py
rook/com_ws/agent_com_impel/singlethread_agent_com.py
rook/com_ws/envelope_wrappers/__init__.py
rook/com_ws/envelope_wrappers/basic_envelope_wrapper.py
rook/com_ws/envelope_wrappers/basic_serialized_envelope_wrapper.py
rook/com_ws/envelope_wrappers/i_envelope_wrapper.py
rook-0.1.209.dist-info/LICENSE
rook-0.1.209.dist-info/METADATA
rook-0.1.209.dist-info/WHEEL
rook-0.1.209.dist-info/top_level.txt
rook-0.1.209.dist-info/RECORD
